gear/__init__.py
gear/acl.py
gear/constants.py
gear/cmd/__init__.py
gear/cmd/geard.py
gear/tests/__init__.py
gear/tests/test_functional.py
gear/tests/test_gear.py
gear-0.16.0.dist-info/AUTHORS
gear-0.16.0.dist-info/LICENSE
gear-0.16.0.dist-info/METADATA
gear-0.16.0.dist-info/WHEEL
gear-0.16.0.dist-info/entry_points.txt
gear-0.16.0.dist-info/pbr.json
gear-0.16.0.dist-info/top_level.txt
gear-0.16.0.dist-info/RECORD
